cookie2json/__init__.py
cookie2json/__main__.py
cookie2json-1.1.dist-info/LICENSE
cookie2json-1.1.dist-info/METADATA
cookie2json-1.1.dist-info/WHEEL
cookie2json-1.1.dist-info/top_level.txt
cookie2json-1.1.dist-info/RECORD
