Metadata-Version: 2.1
Name: cookie2json
Version: 1.1
Summary: format cookies from chrome or firefox to json.
Home-page: https://github.com/mlzxgzy/cookie2json/
Author: Kami
Author-email: kami@kdajv.com
License: MIT
Platform: UNKNOWN
